olaph/__init__.py
olaph/english_normalizer.py
olaph/german_normalizer.py
olaph/olaph.py
olaph/olaph_utils.py
olaph/dictionaries/general.txt
olaph/dictionaries/general_replacements.txt
olaph/dictionaries/de/de.txt
olaph/dictionaries/de/de_abbreviations.txt
olaph/dictionaries/de/de_capitals.txt
olaph/dictionaries/de/de_replacements.txt
olaph/dictionaries/en/en.txt
olaph/dictionaries/en/en_abbreviations.txt
olaph/dictionaries/en/en_capitals.txt
olaph/dictionaries/es/es.txt
olaph/dictionaries/es/es_capitals.txt
olaph/dictionaries/es/es_replacements.txt
olaph/dictionaries/fr/fr.txt
olaph/dictionaries/fr/fr_abbreviations.txt
olaph/dictionaries/fr/fr_capitals.txt
olaph-0.1.6.dist-info/licenses/LICENSE
olaph-0.1.6.dist-info/METADATA
olaph-0.1.6.dist-info/WHEEL
olaph-0.1.6.dist-info/top_level.txt
olaph-0.1.6.dist-info/RECORD
