Metadata-Version: 2.4
Name: olaph
Version: 0.1.6
Summary: A multilingual phonemizer combining lexica, NLP, and probabilistic scoring for improved phonemization accuracy..
Author-email: Johannes Wirth <johannes.wirth.3@iisys.de>
License: MIT
Project-URL: Homepage, https://github.com/iisys-hof/olaph
Project-URL: Documentation, https://github.com/iisys-hof/olaph#readme
Project-URL: Issues, https://github.com/iisys-hof/olaph/issues
Keywords: phonemizer,text-to-speech,linguistics,NLP,multilingual
Classifier: Intended Audience :: Developers
Classifier: Topic :: Text Processing :: Linguistic
Classifier: License :: OSI Approved :: MIT License
Classifier: Programming Language :: Python :: 3
Requires-Python: >=3.10
License-File: LICENSE
Requires-Dist: inflect==7.5.0
Requires-Dist: spacy
Requires-Dist: lingua-language-detector==2.1.1
Requires-Dist: num2words==0.5.14
Requires-Dist: requests==2.32.5
Requires-Dist: annotated-types==0.7.0
Requires-Dist: blis==1.3.0
Requires-Dist: catalogue==2.0.10
Requires-Dist: certifi==2025.10.5
Requires-Dist: charset-normalizer==3.4.3
Requires-Dist: click==8.3.0
Requires-Dist: cloudpathlib==0.22.0
Requires-Dist: colorama==0.4.6
Requires-Dist: confection==0.1.5
Requires-Dist: cymem==2.0.11
Requires-Dist: docopt==0.6.2
Requires-Dist: idna==3.10
Requires-Dist: jinja2==3.1.6
Requires-Dist: langcodes==3.5.0
Requires-Dist: language-data==1.3.0
Requires-Dist: marisa-trie==1.3.1
Requires-Dist: markdown-it-py==4.0.0
Requires-Dist: markupsafe==3.0.3
Requires-Dist: mdurl==0.1.2
Requires-Dist: murmurhash==1.0.13
Requires-Dist: numpy==2.2.0
Requires-Dist: packaging==25.0
Requires-Dist: preshed==3.0.10
Requires-Dist: pydantic==2.11.10
Requires-Dist: pydantic-core==2.33.2
Requires-Dist: pygments==2.19.2
Requires-Dist: rich==14.1.0
Requires-Dist: setuptools==80.9.0
Requires-Dist: shellingham==1.5.4
Requires-Dist: smart-open==7.3.1
Requires-Dist: spacy-legacy==3.0.12
Requires-Dist: spacy-loggers==1.0.5
Requires-Dist: srsly==2.5.1
Requires-Dist: thinc==8.3.6
Requires-Dist: tqdm==4.67.1
Requires-Dist: typer==0.19.2
Requires-Dist: typing-inspection==0.4.2
Requires-Dist: typing-extensions==4.15.0
Requires-Dist: urllib3==2.5.0
Requires-Dist: wasabi==1.1.3
Requires-Dist: weasel==0.4.1
Requires-Dist: wrapt==1.17.3
Requires-Dist: pytest
Provides-Extra: dev
Requires-Dist: pytest; extra == "dev"
Requires-Dist: black; extra == "dev"
Requires-Dist: flake8; extra == "dev"
Dynamic: license-file
